ralph/__init__.py
ralph/__main__.py
ralph/cli.py
ralph/config.py
ralph/runner.py
ralph/ui.py
ralph/executor/__init__.py
ralph/executor/output.py
ralph/executor/prompt.py
ralph/executor/retry.py
ralph/executor/runner.py
ralph/generator/__init__.py
ralph/generator/base.py
ralph/generator/executor.py
ralph/generator/plans.py
ralph/generator/prd.py
ralph/generator/prompt_builder.py
ralph/generator/prompt_loader.py
ralph/generator/templates.py
ralph/generator/validator.py
ralph/input/__init__.py
ralph/input/base.py
ralph/input/config.py
ralph/input/plans.py
ralph/input/prd.py
ralph/input/prompt.py
ralph/parser/__init__.py
ralph/parser/checkbox.py
ralph/parser/markdown.py
ralph/state/__init__.py
ralph/state/identity.py
ralph/state/models.py
ralph/state/store.py
ralph/state/tracker.py
ralph_agent-1.1.1.dist-info/METADATA
ralph_agent-1.1.1.dist-info/WHEEL
ralph_agent-1.1.1.dist-info/entry_points.txt
ralph_agent-1.1.1.dist-info/licenses/LICENSE
ralph_agent-1.1.1.dist-info/RECORD
