Metadata-Version: 2.4
Name: ralph-agent
Version: 1.1.1
Summary: Ralph - Autonomous Claude Code Agent Runner
Project-URL: Homepage, https://github.com/perception30/claude-code-ralph
Project-URL: Documentation, https://github.com/perception30/claude-code-ralph#readme
Project-URL: Repository, https://github.com/perception30/claude-code-ralph
Project-URL: Issues, https://github.com/perception30/claude-code-ralph/issues
Author-email: Khaled Bin A Quadir <perception30@gmail.com>
License-Expression: MIT
License-File: LICENSE
Keywords: agent,ai,autonomous,claude,cli,coding
Classifier: Development Status :: 4 - Beta
Classifier: Environment :: Console
Classifier: Intended Audience :: Developers
Classifier: License :: OSI Approved :: MIT License
Classifier: Operating System :: OS Independent
Classifier: Programming Language :: Python :: 3
Classifier: Programming Language :: Python :: 3.9
Classifier: Programming Language :: Python :: 3.10
Classifier: Programming Language :: Python :: 3.11
Classifier: Programming Language :: Python :: 3.12
Classifier: Topic :: Software Development
Classifier: Topic :: Utilities
Requires-Python: >=3.9
Requires-Dist: pexpect>=4.8.0
Requires-Dist: rich>=13.0.0
Requires-Dist: typer>=0.9.0
Provides-Extra: dev
Requires-Dist: autoflake>=2.0.0; extra == 'dev'
Requires-Dist: black>=23.0.0; extra == 'dev'
Requires-Dist: mypy>=1.0.0; extra == 'dev'
Requires-Dist: pytest-cov>=4.0.0; extra == 'dev'
Requires-Dist: pytest>=7.0.0; extra == 'dev'
Requires-Dist: ruff>=0.1.0; extra == 'dev'
Requires-Dist: vulture>=2.10; extra == 'dev'
